amon/__init__.py
amon/blueprint.py
amon/data/__init__.py
amon/data/elevation_functions/elevation_function_1.py
amon/data/elevation_functions/__pycache__/elevation_function_1.cpython-310.pyc
amon/data/elevation_functions/__pycache__/elevation_function_1.cpython-311.pyc
amon/data/wind_data/wind_data_1/wind_direction.csv
amon/data/wind_data/wind_data_1/wind_speed.csv
amon/data/wind_data/wind_data_2/wind_direction.csv
amon/data/wind_data/wind_data_2/wind_speed.csv
amon/data/wind_data/wind_data_3/wind_direction.csv
amon/data/wind_data/wind_data_3/wind_speed.csv
amon/data/wind_data/wind_data_4/wind_direction.csv
amon/data/wind_data/wind_data_4/wind_speed.csv
amon/data/wind_turbines/wind_turbine_1/powerct_curve.csv
amon/data/wind_turbines/wind_turbine_1/properties.csv
amon/data/wind_turbines/wind_turbine_2/powerct_curve.csv
amon/data/wind_turbines/wind_turbine_2/properties.csv
amon/data/wind_turbines/wind_turbine_3/powerct_curve.csv
amon/data/wind_turbines/wind_turbine_3/properties.csv
amon/data/wind_turbines/wind_turbine_4/powerct_curve.csv
amon/data/wind_turbines/wind_turbine_4/properties.csv
amon/data/wind_turbines/wind_turbine_5/powerct_curve.csv
amon/data/wind_turbines/wind_turbine_5/properties.csv
amon/data/wind_turbines/wind_turbine_6/powerct_curve.csv
amon/data/wind_turbines/wind_turbine_6/properties.csv
amon/data/zones/zone_1/boundary_zone.shp
amon/data/zones/zone_1/exclusion_zone.shp
amon/data/zones/zone_2/boundary_zone.shp
amon/data/zones/zone_2/exclusion_zone.shp
amon/data/zones/zone_3/boundary_zone.shp
amon/data/zones/zone_3/exclusion_zone.shp
amon/data/zones/zone_4/boundary_zone.shp
amon/data/zones/zone_4/exclusion_zone.shp
amon/data/zones/zone_5/boundary_zone.shp
amon/instances/__init__.py
amon/instances/1/params.txt
amon/instances/2/params.txt
amon/instances/3/params.txt
amon/instances/4/params.txt
amon/instances/5/params.txt
amon/instances/6/params.txt
amon/instances/7/params.txt
amon/src/__init__.py
amon/src/argparsing.py
amon/src/blackbox.py
amon_bb-0.4.dist-info/licenses/LICENSE
amon_bb-0.4.dist-info/METADATA
amon_bb-0.4.dist-info/WHEEL
amon_bb-0.4.dist-info/entry_points.txt
amon_bb-0.4.dist-info/top_level.txt
amon_bb-0.4.dist-info/RECORD
