Metadata-Version: 2.4
Name: amon_bb
Version: 0.4
Summary: Wind farm blackbox CLI app
Author-email: Léon Biner <leon.biner@polymtl.ca>
License:                     GNU GENERAL PUBLIC LICENSE
Requires-Python: >=3.7
License-File: LICENSE
Requires-Dist: py_wake>2.6.11
Requires-Dist: numpy
Requires-Dist: matplotlib
Requires-Dist: shapely
Requires-Dist: pathlib
Requires-Dist: requests
Requires-Dist: scipy
Requires-Dist: pandas
Requires-Dist: geopandas
Requires-Dist: windrose
Requires-Dist: pyshp
Requires-Dist: flask
Requires-Dist: xarray
Dynamic: license-file
